Metadata-Version: 2.4
Name: aegis-cli
Version: 2.0.0
Summary: A simple CLI tool to automate the creation of essential security starter files for your projects. Now with expanded language support and automated checks!
Author: JamesTheGiblet
License: # MIT License
Project-URL: Homepage, https://github.com/JamesTheGiblet/Project-Aegis-CLI
Project-URL: Repository, https://github.com/JamesTheGiblet/Project-Aegis-CLI
Project-URL: Issues, https://github.com/JamesTheGiblet/Project-Aegis-CLI/issues
Keywords: security,documentation,automation,cli,devsecops,dependabot,security.md
Classifier: Programming Language :: Python :: 3
Classifier: Programming Language :: Python :: 3.8
Classifier: Programming Language :: Python :: 3.9
Classifier: Programming Language :: Python :: 3.10
Classifier: Programming Language :: Python :: 3.11
Classifier: License :: OSI Approved :: MIT License
Classifier: Operating System :: OS Independent
Classifier: Topic :: Security
Classifier: Topic :: Software Development
Classifier: Topic :: Utilities
Requires-Python: >=3.8
License-File: LICENSE
Requires-Dist: click>=8.0.0
Requires-Dist: Jinja2>=3.0.0
Provides-Extra: test
Requires-Dist: pytest>=7.0.0; extra == "test"
Dynamic: license-file
